rumoderatorai/__init__.py
rumoderatorai/clients.py
rumoderatorai/data.py
rumoderatorai/exceptions.py
rumoderatorai/types.py
rumoderatorai/utils.py
rumoderatorai-1.6.2.dist-info/METADATA
rumoderatorai-1.6.2.dist-info/WHEEL
rumoderatorai-1.6.2.dist-info/top_level.txt
rumoderatorai-1.6.2.dist-info/RECORD
