Metadata-Version: 2.4
Name: rumoderatorai
Version: 1.6.2
Summary: Библиотека для использования Omni Antispam API (https://moderator.omni-devel.ru)
Home-page: https://moderator.omni-devel.ru
Author: PyWebSol
Classifier: Programming Language :: Python :: 3
Classifier: Operating System :: OS Independent
Requires-Python: >=3.8
Requires-Dist: aiohttp
Requires-Dist: Pillow
Requires-Dist: boltons
Dynamic: author
Dynamic: classifier
Dynamic: description
Dynamic: description-content-type
Dynamic: home-page
Dynamic: requires-dist
Dynamic: requires-python
Dynamic: summary
